[
    {
        "pname":"Shahid Salmani",
        "status":"Approved",
        "time":"10:00am",
        "date":"24 Mar"
    },
    {
        "pname":"Suchita Jangali",
        "status":"Pending",
        "time":"7:00pm",
        "date":"12 Mar"
    },
    {
        "pname":"Harish Nagure",
        "status":"Approved",
        "time":"12:00pm",
        "date":"24 Mar"
    },
    {
        "pname":"Mamta Jaiswal",
        "status":"Pending",
        "time":"1:00pm",
        "date":"28 Mar"
    },
    {
        "pname":"Aasiya Siddiq",
        "status":"Approved",
        "time":"1:00pm",
        "date":"24 Mar"
    },
    {
        "pname":"Divya Shetty",
        "status":"Pending",
        "time":"3:00pm",
        "date":"12 Mar"
    },
    {
        "pname":"Shital Patil",
        "status":"Approved",
        "time":"11:00am",
        "date":"24 Mar"
    },
    {
        "pname":"Prajisha Jitesh",
        "status":"Pending",
        "time":"6:00pm",
        "date":"12 Mar"
    }
]